README.rst
setup.py
venus/__init__.py
venus.egg-info/PKG-INFO
venus.egg-info/SOURCES.txt
venus.egg-info/dependency_links.txt
venus.egg-info/top_level.txt